stringdb/__init__.py
stringdb/api.py
stringdb-0.1.5.dist-info/AUTHORS.rst
stringdb-0.1.5.dist-info/LICENSE
stringdb-0.1.5.dist-info/METADATA
stringdb-0.1.5.dist-info/WHEEL
stringdb-0.1.5.dist-info/top_level.txt
stringdb-0.1.5.dist-info/RECORD
