Metadata-Version: 1.2
Name: stringdb
Version: 0.1.5
Summary: Python functions to access the STRING API, a source of protein-protein association networks.
Home-page: https://github.com/gpp-rnd/stringdb
Author: Peter C DeWeirdt
Author-email: petedeweirdt@gmail.com
License: MIT license
Keywords: stringdb
Platform: UNKNOWN
Classifier: Development Status :: 2 - Pre-Alpha
Classifier: Intended Audience :: Developers
Classifier: License :: OSI Approved :: MIT License
Classifier: Natural Language :: English
Classifier: Programming Language :: Python :: 3
Classifier: Programming Language :: Python :: 3.5
Classifier: Programming Language :: Python :: 3.6
Classifier: Programming Language :: Python :: 3.7
Classifier: Programming Language :: Python :: 3.8
Requires-Python: >=3.5
